{
  "projectName": "Example Project",
  "customerName": "Awesome Customer",
  "documentName": "example doc",
  "logoURL": "https://upload.wikimedia.org/wikipedia/commons/a/a9/Example_title.png",
  "fieldDefaultColor": "blue",
  "fields": {
    "locale": {
      "type": "locale",
      "name": "Locale"
    },
    "total_incl": {
      "type": "field",
      "name": "Total (w. tax)",
      "color": "coral"
    },
    "total_excl": {
      "type": "field",
      "name": "Total (w/o tax)",
      "color": "lavender"
    },
    "invoice_date": {
      "type": "field",
      "name": "Date",
      "color": "gold"
    },
    "invoice_number": {
      "type": "field",
      "name": "Number",
      "color": "mauve"
    },
    "due_date": {
      "type": "field",
      "name": "Due",
      "color": "rgb(162, 215, 219)"
    },
    "taxes": {
      "type": "[:field]",
      "name": "Taxes",
      "color": "#00eeff"
    },
    "supplier": {
      "type": "field",
      "name": "Supplier",
      "color": "teal"
    },
    "supplier_address": {
      "type": "field",
      "name": "Locale",
      "color": "orange"
    },
    "customer_name": {
      "type": "field",
      "name": "Customer",
      "color": "purple"
    },
    "customer_company_registration": {
      "type": "field",
      "name": "Customer Registration",
      "color": "red"
    },
    "customer_address": {
      "type": "field",
      "name": "Customer Address",
      "color": "grey"
    },
    "payment_details": {
      "type": "[:field]",
      "name": "Payment Info",
      "color": "dark"
    },
    "company_number": {
      "type": "[:field]",
      "name": "Company Numbers",
      "color": "yellow"
    },
    "total_tax": {
      "type": "field",
      "name": "Total Tax",
      "color": "green"
    },
    "line_items": {
      "type": "[:lineItem]",
      "name": "Line Items",
      "color": "blue",
      "columns": {
        "item_id": {
          "name": "Item"
        },
        "description": {
          "name": "Description"
        },
        "quantity": {
          "name": "QTY"
        },
        "unit_price": {
          "name": "Unit Price"
        },
        "price_amount": {
          "name": "Total Price"
        },
        "upc": {
          "name": "UPC"
        }
      }
    }
  }
}
